PyPCAlg/__init__.py
PyPCAlg/meeks_rules.py
PyPCAlg/pc_algorithm.py
PyPCAlg/checks/__init__.py
PyPCAlg/checks/check_pc_algorithm.py
PyPCAlg/examples/__init__.py
PyPCAlg/examples/graph_1.py
PyPCAlg/examples/graph_2.py
PyPCAlg/examples/graph_3.py
PyPCAlg/examples/graph_4.py
PyPCAlg/examples/oracle_tools.py
PyPCAlg/examples/true_independence_relationships_graph_1.csv
PyPCAlg/examples/true_independence_relationships_graph_2.csv
PyPCAlg/examples/true_independence_relationships_graph_3.csv
PyPCAlg/examples/true_independence_relationships_graph_4.csv
PyPCAlg/test/__init__.py
PyPCAlg/test/test_meeks_rules.py
PyPCAlg/test/test_pc_algorithm.py
PyPCAlg/test/test_utilities_pc_algorithm.py
PyPCAlg/utilities/__init__.py
PyPCAlg/utilities/independence_relationships.py
PyPCAlg/utilities/logs.py
PyPCAlg/utilities/pc_algorithm.py
PyPCAlg/utilities/pdag.py
PyPCAlg-1.0.3.dist-info/LICENSE
PyPCAlg-1.0.3.dist-info/METADATA
PyPCAlg-1.0.3.dist-info/WHEEL
PyPCAlg-1.0.3.dist-info/top_level.txt
PyPCAlg-1.0.3.dist-info/RECORD
