Metadata-Version: 2.1
Name: PyPCAlg
Version: 1.0.3
Summary: A Python implementation of the original PC algorithm.
Home-page: https://github.com/Black-Swan-ICL/PyPCAlg
Author: K. M-H
Author-email: kmh.pro@protonmail.com
License: MIT
Platform: UNKNOWN
Classifier: License :: OSI Approved :: MIT License
Classifier: Programming Language :: Python :: 3
Classifier: Programming Language :: Python :: 3.9
Classifier: Topic :: Scientific/Engineering
Classifier: Topic :: Scientific/Engineering :: Information Analysis
Classifier: Intended Audience :: Science/Research
Classifier: Intended Audience :: Financial and Insurance Industry
Requires-Python: >=3.9
Requires-Dist: numpy (>=1.22.0)
Requires-Dist: pandas
Requires-Dist: matplotlib
Requires-Dist: scikit-learn
Requires-Dist: pingouin
